monitoring/__init__.py
monitoring/internal_temp.py
monitoring/motion_sensing.py
pi_smart_camper-0.0.2.dist-info/LICENSE
pi_smart_camper-0.0.2.dist-info/METADATA
pi_smart_camper-0.0.2.dist-info/WHEEL
pi_smart_camper-0.0.2.dist-info/top_level.txt
pi_smart_camper-0.0.2.dist-info/RECORD
