Metadata-Version: 2.1
Name: pi-smart-camper
Version: 0.0.2
Summary: Source code for a 'smart' Raspberry Pi-powered travel trailer.
Home-page: https://github.com/tBaxter/pi-smart-camper
Author: Carter Baxter
Author-email: mail.baxter@gmail.com
License: UNKNOWN
Platform: UNKNOWN
Classifier: Programming Language :: Python :: 3
Classifier: License :: CC0 1.0 Universal (CC0 1.0) Public Domain Dedication
Classifier: Operating System :: OS Independent
Requires-Python: >=3.6
Requires-Dist: Flask
